Metadata-Version: 2.1
Name: consolespider
Version: 0.4
Summary: Console spider game
Home-page: UNKNOWN
Author-email: oleksiy.saurin@gmail.com
License: UNKNOWN
Platform: UNKNOWN
Requires: termcolor
